word2speech/__init__.py
word2speech/__main__.py
word2speech/cli.py
word2speech/config.py
word2speech/models.py
word2speech/analysis/__init__.py
word2speech/analysis/audio_analyzer.py
word2speech/modules/__init__.py
word2speech/modules/deletrear.py
word2speech/modules/errors.py
word2speech/modules/prosodia.py
word2speech/modules/test_utilities.py
word2speech/modules/transformer.py
word2speech/modules/utilities.py
word2speech/plugins/__init__.py
word2speech/plugins/mms_tts.py
word2speech/plugins/parler_tts.py
word2speech/plugins/speechgen.py
word2speech-2.0.1.dist-info/licenses/LICENSE
word2speech-2.0.1.dist-info/METADATA
word2speech-2.0.1.dist-info/WHEEL
word2speech-2.0.1.dist-info/entry_points.txt
word2speech-2.0.1.dist-info/top_level.txt
word2speech-2.0.1.dist-info/RECORD
