Metadata-Version: 2.4
Name: word2speech
Version: 2.0.1
Summary: Herramienta CLI para el manejo de modelos TTS
Author-email: Alejandro Varela de Cora <alejandrodecora@gmail.com>
License-Expression: GPL-3.0-only
Project-URL: Homepage, https://github.com/adecora/proyecto-dislexia
Project-URL: Repository, https://github.com/adecora/proyecto-dislexia
Requires-Python: >=3.12
License-File: LICENSE
Requires-Dist: PyYAML>=6.0.0
Requires-Dist: requests>=2.32.0
Requires-Dist: silabeador>=1.2.1
Requires-Dist: epitran>=1.26.0
Requires-Dist: click>=8.0.0
Provides-Extra: analyze
Requires-Dist: torch>=2.0.0; extra == "analyze"
Requires-Dist: librosa>=0.11.0; extra == "analyze"
Provides-Extra: local-models
Requires-Dist: torch>=2.0.0; extra == "local-models"
Requires-Dist: transformers>=4.30.0; extra == "local-models"
Requires-Dist: soundfile>=0.12.0; extra == "local-models"
Requires-Dist: parler-tts>=0.1.0; extra == "local-models"
Requires-Dist: llvmlite>=0.42.0; extra == "local-models"
Requires-Dist: numba>=0.58.0; extra == "local-models"
Provides-Extra: all
Requires-Dist: word2speech[analyze,local-models]; extra == "all"
Dynamic: license-file
